.DS_Store
emailnetwork/__init__.py
emailnetwork/emails.py
emailnetwork/extract.py
emailnetwork/graph.py
emailnetwork/header.py
emailnetwork/network.py
emailnetwork/summary.py
emailnetwork/utils.py
emailnetwork/version.py
emailnetwork/tests/__init__.py
emailnetwork/tests/test.mbox
emailnetwork/tests/test_extract.py
emailnetwork/tests/test_graph.py
emailnetwork/tests/test_summary.py
emailnetwork/tests/test_utils.py
emailnetwork-0.0.2.dist-info/LICENSE
emailnetwork-0.0.2.dist-info/METADATA
emailnetwork-0.0.2.dist-info/WHEEL
emailnetwork-0.0.2.dist-info/top_level.txt
emailnetwork-0.0.2.dist-info/RECORD
