Metadata-Version: 2.1
Name: emailnetwork
Version: 0.0.2
Summary: Network graphing utilities for email/mailbox (.mbox) data
Home-page: http://github.com/onlyphantom/emailnetwork
Author: Samuel Chan
Author-email: s@supertype.ai
License: MIT
Platform: UNKNOWN
Classifier: License :: OSI Approved :: MIT License
Classifier: Programming Language :: Python :: 3
Classifier: Programming Language :: Python :: 3.7
Classifier: Operating System :: OS Independent
Requires-Python: >=3.7
Requires-Dist: matplotlib
Requires-Dist: networkx
